Workbook
Name \a: #REF!
Name \b: #REF!
Name \I: #REF!
Name \P: #REF!
Name _: #REF!,#REF!,#REF!,#REF!,#REF!,#REF!,#REF!,#REF!,#REF!,#REF!
Name _______ISC3: #REF!+#REF!
Name ______ISC3: #REF!+#REF!
Name _____ISC3: #REF!+#REF!
Name ____ISC3: #REF!+#REF!
Name ___ISC3: #REF!+#REF!
Name __123Graph_A: #REF!
Name __123Graph_ABERLGRAP: #REF!
Name __123Graph_ACATCH1: #REF!
Name __123Graph_ACONVERG1: #REF!
Name __123Graph_AECTOT: #REF!
Name __123Graph_AGRAPH2: #REF!
Name __123Graph_AGRAPH41: #REF!
Name __123Graph_AGRAPH42: #REF!
Name __123Graph_AGRAPH44: #REF!
Name __123Graph_APERIB: #REF!
Name __123Graph_APRODABSC: #REF!
Name __123Graph_APRODABSD: #REF!
Name __123Graph_APRODTRE2: #REF!
Name __123Graph_APRODTRE3: #REF!
Name __123Graph_APRODTRE4: #REF!
Name __123Graph_APRODTREND: #REF!
Name __123Graph_AUTRECHT: #REF!
Name __123Graph_B: #REF!
Name __123Graph_BBERLGRAP: #REF!
Name __123Graph_BCATCH1: #REF!
Name __123Graph_BCONVERG1: #REF!
Name __123Graph_BECTOT: #REF!
Name __123Graph_BGRAPH2: #REF!
Name __123Graph_BGRAPH41: #REF!
Name __123Graph_BPERIB: #REF!
Name __123Graph_BPRODABSC: #REF!
Name __123Graph_BPRODABSD: #REF!
Name __123Graph_C: #REF!
Name __123Graph_CBERLGRAP: #REF!
Name __123Graph_CCATCH1: #REF!
Name __123Graph_CCONVERG1: #REF!
Name __123Graph_CECTOT: #REF!
Name __123Graph_CGRAPH41: #REF!
Name __123Graph_CGRAPH44: #REF!
Name __123Graph_CPERIA: #REF!
Name __123Graph_CPERIB: #REF!
Name __123Graph_CPRODABSC: #REF!
Name __123Graph_CPRODTRE2: #REF!
Name __123Graph_CPRODTREND: #REF!
Name __123Graph_CUTRECHT: #REF!
Name __123Graph_D: #REF!
Name __123Graph_DBERLGRAP: #REF!
Name __123Graph_DCATCH1: #REF!
Name __123Graph_DCONVERG1: #REF!
Name __123Graph_DECTOT: #REF!
Name __123Graph_DGRAPH41: #REF!
Name __123Graph_DPERIA: #REF!
Name __123Graph_DPERIB: #REF!
Name __123Graph_DPRODABSC: #REF!
Name __123Graph_DUTRECHT: #REF!

Sheet Sheet1
A1: 同通胀数据区 | W1: 财政数据区
A2: 单位：% | B2: 较上月变化 | D2: =[1]物价数据快报!E5 -> 46203 | E2: =[1]物价数据快报!F5 -> 46173 | F2: =[1]物价数据快报!G5 -> 46142 | G2: =[1]物价数据快报!H5 -> 46112 | H2: =[1]物价数据快报!I5 -> 46081 | I2: =[1]物价数据快报!J5 -> 46053 | J2: =[1]物价数据快报!K5 -> 46022 | K2: =[1]物价数据快报!L5 -> 45991 | ... S2: =[1]物价数据快报!T5 -> 45747 | U2: 较上月变化 | W2: =[2]一图!E10 -> 46203 | X2: =[2]一图!F10 -> 46173 | Y2: =[2]一图!G10 -> 46142 | Z2: =[2]一图!H10 -> 46112 | AA2: =[2]一图!I10 -> 46081 | AB2: =[2]一图!J10 -> 46022 | AC2: =[2]一图!K10 -> 45991 | AD2: =[2]一图!L10 -> 45961 | ... AI2: =[2]一图!Q10 -> 45808
A3: CPI同比 | B3: =C3 -> -0.2 | C3: =D3-E3 -> -0.2 | D3: =[1]物价数据快报!E6 -> 1 | E3: =[1]物价数据快报!F6 -> 1.2 | F3: =[1]物价数据快报!G6 -> 1.2 | G3: =[1]物价数据快报!H6 -> 1 | H3: =[1]物价数据快报!I6 -> 1.3 | I3: =[1]物价数据快报!J6 -> 0.2 | J3: =[1]物价数据快报!K6 -> 0.8 | K3: =[1]物价数据快报!L6 -> 0.7 | ... S3: =[1]物价数据快报!T6 -> -0.1 | U3: =X3-W3 -> -2.0676534 | V3: 公共财政收入 | W3: =[2]一图!E11 -> 8.6522726 | X3: =[2]一图!F11 -> 6.5846192 | Y3: =[2]一图!G11 -> 6.6774367 | Z3: =[2]一图!H11 -> 6.8940182 | AA3: =[2]一图!I11 -> 0.67949653 | AB3: =[2]一图!J11 -> -24.951672 | AC3: =[2]一图!K11 -> -0.021384275 | AD3: =[2]一图!L11 -> 3.1566463 | ... AI3: =[2]一图!Q11 -> 0.13136494
A4: 核心 | B4: =C4 -> -0.1 | C4: =D4-E4 -> -0.1 | D4: =[1]物价数据快报!E7 -> 1 | E4: =[1]物价数据快报!F7 -> 1.1 | F4: =[1]物价数据快报!G7 -> 1.2 | G4: =[1]物价数据快报!H7 -> 1.1 | H4: =[1]物价数据快报!I7 -> 1.8 | I4: =[1]物价数据快报!J7 -> 0.8 | J4: =[1]物价数据快报!K7 -> 1.2 | K4: =[1]物价数据快报!L7 -> 1.2 | ... S4: =[1]物价数据快报!T7 -> 0.5 | U4: =X4-W4 -> -7.2961356 | V4: 其中：中央财政收入 | W4: =[2]一图!E12 -> 18.119105 | X4: =[2]一图!F12 -> 10.822969 | Y4: =[2]一图!G12 -> 9.2434348 | Z4: =[2]一图!H12 -> 20.504862 | AA4: =[2]一图!I12 -> -1.7026514 | AB4: =[2]一图!J12 -> -50.253302 | AC4: =[2]一图!K12 -> -4.2318841 | AD4: =[2]一图!L12 -> 2.2929818 | ... AI4: =[2]一图!Q12 -> 0.39851222
A5: 食品 | B5: =C5 -> 0.1 | C5: =D5-E5 -> 0.1 | D5: =[1]物价数据快报!E8 -> -1.6 | E5: =[1]物价数据快报!F8 -> -1.7 | F5: =[1]物价数据快报!G8 -> -1.6 | G5: =[1]物价数据快报!H8 -> 0.3 | H5: =[1]物价数据快报!I8 -> 1.7 | I5: =[1]物价数据快报!J8 -> -0.7 | J5: =[1]物价数据快报!K8 -> 1.1 | K5: =[1]物价数据快报!L8 -> 0.2 | ... S5: =[1]物价数据快报!T8 -> -1.4 | U5: =X5-W5 -> -0.179743 | V5: 地方财政收入 | W5: =[2]一图!E13 -> 2.972973 | X5: =[2]一图!F13 -> 2.79323 | Y5: =[2]一图!G13 -> 4.4040255 | Z5: =[2]一图!H13 -> 1.173913 | AA5: =[2]一图!I13 -> 2.5865254 | AB5: =[2]一图!J13 -> 4.0672339 | AC5: =[2]一图!K13 -> 4.0538645 | AD5: =[2]一图!L13 -> 3.9910314 | ... AI5: =[2]一图!Q13 -> -0.10640813
A6: 非食品 | B6: =C6 -> -0.4 | C6: =D6-E6 -> -0.4 | D6: =[1]物价数据快报!E9 -> 1.5 | E6: =[1]物价数据快报!F9 -> 1.9 | F6: =[1]物价数据快报!G9 -> 1.8 | G6: =[1]物价数据快报!H9 -> 1.2 | H6: =[1]物价数据快报!I9 -> 1.3 | I6: =[1]物价数据快报!J9 -> 0.4 | J6: =[1]物价数据快报!K9 -> 0.8 | K6: =[1]物价数据快报!L9 -> 0.8 | ... S6: =[1]物价数据快报!T9 -> 0.2 | U6: =X6-W6 -> -4.0573015 | V6: 其中：税收收入 | W6: =[2]一图!E14 -> 10.822007 | X6: =[2]一图!F14 -> 6.7647059 | Y6: =[2]一图!G14 -> 8.2072241 | Z6: =[2]一图!H14 -> 9.1072876 | AA6: =[2]一图!I14 -> 0.12104872 | AB6: =[2]一图!J14 -> -11.501916 | AC6: =[2]一图!K14 -> 2.7827648 | AD6: =[2]一图!L14 -> 8.5645356 | ... AI6: =[2]一图!Q14 -> 0.56196392
A7: CPI环比 | B7: =C7 -> -0.2 | C7: =D7-E7 -> -0.2 | D7: =[1]物价数据快报!E10 -> -0.3 | E7: =[1]物价数据快报!F10 -> -0.1 | F7: =[1]物价数据快报!G10 -> 0.3 | G7: =[1]物价数据快报!H10 -> -0.7 | H7: =[1]物价数据快报!I10 -> 1 | I7: =[1]物价数据快报!J10 -> 0.2 | J7: =[1]物价数据快报!K10 -> 0.2 | K7: =[1]物价数据快报!L10 -> -0.1 | ... S7: =[1]物价数据快报!T10 -> -0.4 | U7: =X7-W7 -> 2.6735775 | V7: 非税收入 | W7: =[2]一图!E15 -> 2.8935185 | X7: =[2]一图!F15 -> 5.567096 | Y7: =[2]一图!G15 -> -5.256355 | Z7: =[2]一图!H15 -> 2.1980122 | AA7: =[2]一图!I15 -> 3.3835087 | AB7: =[2]一图!J15 -> -47.919393 | AC7: =[2]一图!K15 -> -10.834199 | AD7: =[2]一图!L15 -> -32.95972 | ... AI7: =[2]一图!Q15 -> -2.2339561
A8: 核心 | B8: =C8 -> 0 | C8: =D8-E8 -> 0 | D8: =[1]物价数据快报!E11 -> -0.1 | E8: =[1]物价数据快报!F11 -> -0.1 | F8: =[1]物价数据快报!G11 -> 0.2 | G8: =[1]物价数据快报!H11 -> -0.7 | H8: =[1]物价数据快报!I11 -> 0.7 | I8: =[1]物价数据快报!J11 -> 0.3 | J8: =[1]物价数据快报!K11 -> 0.2 | K8: =[1]物价数据快报!L11 -> -0.1 | ... S8: =[1]物价数据快报!T11 -> 0 | U8: =X8-W8 -> -5.5737953 | V8: 公共财政支出 | W8: =[2]一图!E16 -> 4.0045201 | X8: =[2]一图!F16 -> -1.5692752 | Y8: =[2]一图!G16 -> -3.1927189 | Z8: =[2]一图!H16 -> 1.0137451 | AA8: =[2]一图!I16 -> 3.5701614 | AB8: =[2]一图!J16 -> -1.7745646 | AC8: =[2]一图!K16 -> -3.7095133 | AD8: =[2]一图!L16 -> -9.7785228 | ... AI8: =[2]一图!Q16 -> 2.6276754
A9: 食品 | B9: =C9 -> 0 | C9: =D9-E9 -> 0 | D9: =[1]物价数据快报!E12 -> -0.4 | E9: =[1]物价数据快报!F12 -> -0.4 | F9: =[1]物价数据快报!G12 -> -0.1 | G9: =[1]物价数据快报!H12 -> 0.4 | H9: =[1]物价数据快报!I12 -> 0.5 | I9: =[1]物价数据快报!J12 -> -0.7 | J9: =[1]物价数据快报!K12 -> -1.5 | K9: =[1]物价数据快报!L12 -> -1.7 | ... S9: =[1]物价数据快报!T12 -> -1.5 | U9: =X9-W9 -> 4.4364822 | V9: 其中：中央财政支出 | W9: =[2]一图!E17 -> 6.8170791 | X9: =[2]一图!F17 -> 11.253561 | Y9: =[2]一图!G17 -> 5.4978962 | Z9: =[2]一图!H17 -> 5.6978417 | AA9: =[2]一图!I17 -> 4.4639451 | AB9: =[2]一图!J17 -> 1.7372881 | AC9: =[2]一图!K17 -> 4.877319 | AD9: =[2]一图!L17 -> -0.98509052 | ... AI9: =[2]一图!Q17 -> 11.04081
A10: 非食品 | B10: =C10 -> -1.6 | C10: =D10-E10 -> -1.6 | D10: =[1]物价数据快报!E13 -> -0.3 | E10: =[1]物价数据快报!F13 -> 1.3 | F10: =[1]物价数据快报!G13 -> 1.1 | G10: =[1]物价数据快报!H13 -> 0.9 | H10: =[1]物价数据快报!I13 -> 0.8 | I10: =[1]物价数据快报!J13 -> 0.4 | J10: =[1]物价数据快报!K13 -> 0.4 | K10: =[1]物价数据快报!L13 -> 0.3 | ... S10: =[1]物价数据快报!T13 -> 0.2 | U10: =X10-W10 -> -7.9321344 | V10: 地方财政支出 | W10: =[2]一图!E18 -> 3.5253761 | X10: =[2]一图!F18 -> -4.4067583 | Y10: =[2]一图!G18 -> -4.9938957 | Z10: =[2]一图!H18 -> 0.34235275 | AA10: =[2]一图!I18 -> 3.452602 | AB10: =[2]一图!J18 -> -2.2503516 | AC10: =[2]一图!K18 -> -5.1269387 | AD10: =[2]一图!L18 -> -11.851852 | ... AI10: =[2]一图!Q18 -> 0.93541203
A11: PPI同比 | B11: =C11 -> 0.2 | C11: =D11-E11 -> 0.2 | D11: =[1]物价数据快报!E14 -> 4.1 | E11: =[1]物价数据快报!F14 -> 3.9 | F11: =[1]物价数据快报!G14 -> 2.8 | G11: =[1]物价数据快报!H14 -> 0.5 | H11: =[1]物价数据快报!I14 -> -0.9 | I11: =[1]物价数据快报!J14 -> -1.4 | J11: =[1]物价数据快报!K14 -> -1.9 | K11: =[1]物价数据快报!L14 -> -2.2 | ... S11: =[1]物价数据快报!T14 -> -2.5 | U11: =X11-W11 -> 10.881888 | V11: 政府性基金收入 | W11: =[2]一图!E19 -> -31.144228 | X11: =[2]一图!F19 -> -20.26234 | Y11: =[2]一图!G19 -> -26.415094 | Z11: =[2]一图!H19 -> -16.678297 | AA11: =[2]一图!I19 -> -15.953612 | AB11: =[2]一图!J19 -> -11.711073 | AC11: =[2]一图!K19 -> -15.756608 | AD11: =[2]一图!L19 -> -18.365573 | ... AI11: =[2]一图!Q19 -> -8.148383
A12: 生产资料 | B12: =C12 -> 0.3 | C12: =D12-E12 -> 0.3 | D12: =[1]物价数据快报!E15 -> 5.5 | E12: =[1]物价数据快报!F15 -> 5.2 | F12: =[1]物价数据快报!G15 -> 3.8 | G12: =[1]物价数据快报!H15 -> 1 | H12: =[1]物价数据快报!I15 -> -0.7 | I12: =[1]物价数据快报!J15 -> -1.3 | J12: =[1]物价数据快报!K15 -> -2.1 | K12: =[1]物价数据快报!L15 -> -2.4 | ... S12: =[1]物价数据快报!T15 -> -2.8 | U12: =X12-W12 -> 6.3857026 | V12: 其中:土地使用权出让收入 | W12: =[2]一图!E20 -> -42.140468 | X12: =[2]一图!F20 -> -35.754766 | Y12: =[2]一图!G20 -> -34.765155 | Z12: =[2]一图!H20 -> -22.612827 | AA12: =[2]一图!I20 -> -25.231872 | AB12: =[2]一图!J20 -> -22.858209 | AC12: =[2]一图!K20 -> -26.843501 | AD12: =[2]一图!L20 -> -27.252986 | ... AI12: =[2]一图!Q20 -> -14.643799
A13: 生活资料 | B13: =C13 -> -0.1 | C13: =D13-E13 -> -0.1 | D13: =[1]物价数据快报!E16 -> -0.9 | E13: =[1]物价数据快报!F16 -> -0.8 | F13: =[1]物价数据快报!G16 -> -1 | G13: =[1]物价数据快报!H16 -> -1.3 | H13: =[1]物价数据快报!I16 -> -1.6 | I13: =[1]物价数据快报!J16 -> -1.7 | J13: =[1]物价数据快报!K16 -> -1.3 | K13: =[1]物价数据快报!L16 -> -1.5 | ... S13: =[1]物价数据快报!T16 -> -1.5 | U13: =X13-W13 -> 32.205548 | V13: 政府性基金支出 | W13: =[2]一图!E21 -> -43.659881 | X13: =[2]一图!F21 -> -11.454333 | Y13: =[2]一图!G21 -> -20.779017 | Z13: =[2]一图!H21 -> -14.243253 | AA13: =[2]一图!I21 -> 15.98873 | AB13: =[2]一图!J21 -> 1.5166341 | AC13: =[2]一图!K21 -> 2.7536364 | AD13: =[2]一图!L21 -> -38.213066 | ... AI13: =[2]一图!Q21 -> 8.7722485
A14: PPI环比 | B14: =C14 -> -0.8 | C14: =D14-E14 -> -0.8 | D14: =[1]物价数据快报!E17 -> -0.3 | E14: =[1]物价数据快报!F17 -> 0.5 | F14: =[1]物价数据快报!G17 -> 1.7 | G14: =[1]物价数据快报!H17 -> 1 | H14: =[1]物价数据快报!I17 -> 0.4 | I14: =[1]物价数据快报!J17 -> 0.4 | J14: =[1]物价数据快报!K17 -> 0.2 | K14: =[1]物价数据快报!L17 -> 0.1 | ... S14: =[1]物价数据快报!T17 -> -0.4
A15: 生产资料 | B15: =C15 -> -1 | C15: =D15-E15 -> -1 | D15: =[1]物价数据快报!E18 -> -0.3 | E15: =[1]物价数据快报!F18 -> 0.7 | F15: =[1]物价数据快报!G18 -> 2.1 | G15: =[1]物价数据快报!H18 -> 1.3 | H15: =[1]物价数据快报!I18 -> 0.5 | I15: =[1]物价数据快报!J18 -> 0.5 | J15: =[1]物价数据快报!K18 -> 0.3 | K15: =[1]物价数据快报!L18 -> 0.1 | ... S15: =[1]物价数据快报!T18 -> -0.4
A16: 生活资料 | B16: =C16 -> -0.3 | C16: =D16-E16 -> -0.3 | D16: =[1]物价数据快报!E19 -> -0.3 | E16: =[1]物价数据快报!F19 -> 0 | F16: =[1]物价数据快报!G19 -> -0.1 | G16: =[1]物价数据快报!H19 -> -0.1 | H16: =[1]物价数据快报!I19 -> 0 | I16: =[1]物价数据快报!J19 -> 0.1 | J16: =[1]物价数据快报!K19 -> 0 | K16: =[1]物价数据快报!L19 -> 0 | ... S16: =[1]物价数据快报!T19 -> -0.4
A125: 资料来源：wind，华福证券研究所，以上信息来自公开资料整理，不构成任何投资建议
